{
  "電": 41134,
  "部": 34909,
  "記": 32318,
  "第": 29647,
  "前": 24949,
  "図": 24892,
  "子": 24523,
  "体": 22880,
  "置": 22823,
  "形": 21939,
  "成": 21886,
  "示": 20674,
  "出": 17236,
  "導": 17018,
  "面": 16458,
  "上": 16434,
  "光": 16062,
  "装": 15980,
  "層": 15880,
  "定": 14530,
  "実": 14339,
  "回": 14112,
  "方": 13573,
  "分": 13184,
  "力": 12950,
  "信": 12915,
  "態": 12882,
  "基": 12478,
  "素": 12307,
  "極": 12163,
  "合": 12126,
  "発": 11953,
  "表": 11931,
  "明": 11921,
  "域": 11865,
  "側": 11844,
  "板": 11837,
  "数": 11383,
  "間": 11370,
  "施": 11260,
  "路": 10907,
  "端": 10789,
  "構": 10658,
  "半": 10655,
  "例": 10649,
  "領": 10446,
  "一": 9866,
  "本": 9861,
  "制": 9811,
  "位": 9674,
  "波": 9515,
  "号": 9369,
  "接": 9338,
  "用": 9321,
  "動": 9286,
  "圧": 9266,
  "時": 9216,
  "向": 9109,
  "設": 9077,
  "対": 8932,
  "度": 8592,
  "行": 8538,
  "流": 8493,
  "入": 8250,
  "御": 8018,
  "型": 8003,
  "変": 7856,
  "状": 7714,
  "配": 7710,
  "下": 7650,
  "線": 7627,
  "理": 7291,
  "化": 6967,
  "及": 6639,
  "以": 6637,
  "生": 6628,
  "有": 6593,
  "的": 6586,
  "特": 6582,
  "値": 6537,
  "続": 6495,
  "粒": 6314,
  "求": 6274,
  "場": 6219,
  "印": 6040,
  "縁": 5912,
  "処": 5902,
  "性": 5803,
  "通": 5755,
  "高": 5738,
  "射": 5694,
  "画": 5606,
  "膜": 5602,
  "項": 5559,
  "機": 5522,
  "音": 5491,
  "同": 5478,
  "絶": 5466,
  "請": 5344,
  "作": 5330,
  "中": 5326,
  "内": 5290,
  "材": 5212,
  "正": 5204,
  "周": 5137,
  "外": 5125,
  "応": 5102,
  "検": 4950,
  "複": 4887,
  "能": 4868,
  "手": 4808,
  "報": 4806,
  "段": 4720,
  "測": 4672,
  "大": 4565,
  "取": 4443,
  "得": 4250,
  "刷": 4247,
  "係": 4243,
  "像": 4215,
  "受": 4192,
  "備": 4158,
  "造": 4126,
  "次": 4108,
  "情": 4104,
  "晶": 4072,
  "器": 4058,
  "源": 4053,
  "長": 4016,
  "説": 3991,
  "法": 3977,
  "結": 3957,
  "液": 3929,
  "計": 3863,
  "平": 3863,
  "照": 3859,
  "気": 3833,
  "様": 3761,
  "後": 3752,
  "等": 3722,
  "可": 3707,
  "物": 3643,
  "比": 3619,
  "量": 3567,
  "加": 3522,
  "反": 3482,
  "色": 3428,
  "各": 3403,
  "低": 3362,
  "含": 3345,
  "所": 3333,
  "幅": 3199,
  "算": 3169,
  "付": 3085,
  "切": 3078,
  "送": 3048,
  "載": 3031,
  "相": 3012,
  "解": 2988,
  "散": 2975,
  "要": 2966,
  "開": 2940,
  "換": 2928,
  "果": 2919,
  "人": 2909,
  "直": 2892,
  "過": 2845,
  "積": 2835,
  "熱": 2784,
  "込": 2758,
  "程": 2753,
  "持": 2721,
  "質": 2714,
  "離": 2684,
  "主": 2663,
  "駆": 2646,
  "現": 2609,
  "差": 2595,
  "振": 2586,
  "全": 2585,
  "点": 2578,
  "囲": 2574,
  "何": 2549,
  "効": 2546,
  "無": 2533,
  "転": 2514,
  "期": 2497,
  "断": 2472,
  "料": 2471,
  "工": 2456,
  "共": 2430,
  "少": 2422,
  "判": 2397,
  "率": 2388,
  "移": 2386,
  "当": 2360,
  "不": 2353,
  "製": 2351,
  "目": 2346,
  "止": 2323,
  "調": 2322,
  "最": 2319,
  "格": 2296,
  "列": 2284,
  "析": 2270,
  "式": 2266,
  "容": 2264,
  "保": 2248,
  "更": 2246,
  "演": 2242,
  "校": 2214,
  "金": 2210,
  "補": 2209,
  "固": 2176,
  "述": 2143,
  "負": 2119,
  "介": 2111,
  "界": 2079,
  "重": 2076,
  "透": 2073,
  "折": 2060,
  "他": 2042,
  "拡": 2037,
  "選": 2034,
  "自": 1999,
  "指": 1976,
  "膨": 1965,
  "許": 1941,
  "異": 1932,
  "較": 1926,
  "見": 1920,
  "徴": 1918,
  "在": 1904,
  "限": 1889,
  "先": 1882,
  "属": 1878,
  "地": 1846,
  "者": 1844,
  "別": 1833,
  "供": 1832,
  "従": 1828,
  "範": 1825,
  "連": 1810,
  "減": 1806,
  "択": 1803,
  "私": 1799,
  "来": 1794,
  "文": 1783,
  "関": 1762,
  "学": 1754,
  "事": 1731,
  "口": 1728,
  "参": 1720,
  "知": 1712,
  "日": 1695,
  "操": 1688,
  "小": 1672,
  "整": 1650,
  "憶": 1649,
  "放": 1629,
  "略": 1627,
  "集": 1621,
  "又": 1616,
  "査": 1596,
  "炭": 1591,
  "起": 1591,
  "軸": 1581,
  "着": 1574,
  "延": 1564,
  "収": 1547,
  "楽": 1545,
  "献": 1544,
  "確": 1536,
  "視": 1519,
  "強": 1517,
  "厚": 1504,
  "使": 1500,
  "好": 1489,
  "二": 1454,
  "今": 1454,
  "交": 1453,
  "空": 1441,
  "適": 1434,
  "荷": 1427,
  "言": 1425,
  "具": 1418,
  "決": 1417,
  "必": 1380,
  "抑": 1375,
  "該": 1373,
  "帯": 1362,
  "酸": 1354,
  "珪": 1353,
  "際": 1351,
  "近": 1333,
  "濃": 1331,
  "準": 1331,
  "抗": 1327,
  "活": 1298,
  "録": 1288,
  "被": 1283,
  "給": 1282,
  "価": 1279,
  "奏": 1278,
  "抵": 1276,
  "術": 1269,
  "走": 1269,
  "助": 1264,
  "充": 1259,
  "技": 1249,
  "終": 1246,
  "角": 1235,
  "増": 1219,
  "題": 1214,
  "達": 1212,
  "覆": 1209,
  "支": 1205,
  "種": 1202,
  "常": 1196,
  "捕": 1194,
  "純": 1187,
  "単": 1167,
  "順": 1163,
  "池": 1159,
  "心": 1159,
  "両": 1152,
  "意": 1149,
  "閾": 1145,
  "互": 1141,
  "俺": 1139,
  "媒": 1138,
  "末": 1138,
  "張": 1131,
  "伝": 1130,
  "乱": 1129,
  "観": 1127,
  "速": 1125,
  "系": 1112,
  "焼": 1107,
  "戦": 1097,
  "感": 1093,
  "再": 1084,
  "立": 1083,
  "割": 1075,
  "薄": 1074,
  "組": 1074,
  "刻": 1070,
  "裏": 1057,
  "距": 1048,
  "左": 1048,
  "認": 1036,
  "品": 1036,
  "良": 1033,
  "課": 1029,
  "細": 1029,
  "察": 1019,
  "曲": 1017,
  "排": 1015,
  "捉": 1010,
  "多": 1005,
  "管": 996,
  "番": 994,
  "温": 992,
  "思": 988,
  "短": 986,
  "納": 983,
  "君": 979,
  "突": 978,
  "護": 971,
  "始": 961,
  "了": 946,
  "件": 935,
  "右": 917,
  "畳": 914,
  "衛": 913,
  "誘": 907,
  "個": 896,
  "辺": 892,
  "並": 891,
  "利": 891,
  "偏": 889,
  "防": 889,
  "停": 884,
  "星": 884,
  "巻": 879,
  "白": 877,
  "進": 870,
  "誤": 870,
  "存": 868,
  "布": 866,
  "横": 859,
  "脂": 858,
  "押": 857,
  "樹": 856,
  "象": 854,
  "書": 853,
  "考": 851,
  "元": 849,
  "模": 848,
  "評": 848,
  "佐": 841,
  "公": 829,
  "提": 827,
  "標": 826,
  "除": 825,
  "沿": 823,
  "待": 821,
  "引": 819,
  "国": 812,
  "字": 809,
  "逆": 807,
  "読": 792,
  "安": 790,
  "隣": 788,
  "干": 785,
  "壁": 785,
  "束": 784,
  "微": 783,
  "触": 782,
  "経": 774,
  "泡": 773,
  "鍵": 771,
  "貫": 770,
  "筐": 769,
  "概": 767,
  "鏡": 766,
  "予": 756,
  "渉": 754,
  "試": 751,
  "底": 750,
  "凹": 748,
  "規": 740,
  "省": 739,
  "与": 739,
  "径": 734,
  "名": 730,
  "原": 726,
  "車": 726,
  "撮": 718,
  "士": 715,
  "消": 713,
  "密": 709,
  "針": 700,
  "詳": 695,
  "風": 690,
  "初": 690,
  "残": 689,
  "息": 687,
  "会": 685,
  "僕": 675,
  "区": 668,
  "水": 667,
  "斜": 663,
  "殺": 659,
  "耐": 651,
  "返": 647,
  "孔": 643,
  "死": 643,
  "失": 633,
  "約": 627,
  "削": 623,
  "新": 618,
  "違": 614,
  "絡": 613,
  "世": 612,
  "覚": 612,
  "撃": 601,
  "男": 595,
  "非": 593,
  "望": 591,
  "均": 589,
  "類": 589,
  "磁": 588,
  "円": 588,
  "識": 588,
  "女": 587,
  "符": 585,
  "刃": 585,
  "蓋": 584,
  "我": 583,
  "藤": 581,
  "命": 579,
  "副": 576,
  "凸": 575,
  "露": 575,
  "声": 575,
  "道": 573,
  "員": 572,
  "隔": 571,
  "去": 568,
  "深": 567,
  "警": 563,
  "隊": 561,
  "圭": 557,
  "問": 556,
  "否": 554,
  "易": 553,
  "乗": 552,
  "青": 551,
  "傾": 551,
  "退": 550,
  "背": 550,
  "仕": 547,
  "味": 547,
  "注": 545,
  "替": 545,
  "条": 533,
  "簡": 533,
  "超": 528,
  "話": 524,
  "業": 520,
  "混": 519,
  "満": 519,
  "戻": 517,
  "遷": 516,
  "軍": 515,
  "遅": 514,
  "夫": 514,
  "黒": 512,
  "遮": 506,
  "難": 506,
  "総": 499,
  "野": 496,
  "欠": 494,
  "寄": 490,
  "顕": 481,
  "広": 480,
  "弾": 479,
  "倍": 479,
  "代": 478,
  "破": 477,
  "登": 475,
  "繰": 473,
  "携": 473,
  "勤": 471,
  "優": 471,
  "挟": 470,
  "励": 469,
  "脱": 468,
  "縦": 467,
  "冷": 464,
  "精": 462,
  "市": 460,
  "令": 459,
  "赤": 457,
  "年": 455,
  "民": 450,
  "任": 448,
  "台": 447,
  "輝": 445,
  "吹": 444,
  "描": 441,
  "義": 439,
  "都": 438,
  "想": 437,
  "妖": 435,
  "縞": 434,
  "亜": 434,
  "緑": 433,
  "損": 433,
  "彼": 433,
  "未": 432,
  "十": 429,
  "和": 427,
  "論": 427,
  "告": 426,
  "却": 425,
  "到": 424,
  "挿": 422,
  "般": 422,
  "溶": 417,
  "井": 416,
  "悪": 416,
  "称": 414,
  "誰": 412,
  "崎": 408,
  "衡": 407,
  "添": 405,
  "改": 404,
  "封": 403,
  "影": 401,
  "完": 401,
  "吸": 400,
  "身": 399,
  "局": 398,
  "塗": 396,
  "練": 394,
  "由": 394,
  "答": 392,
  "願": 392,
  "魔": 392,
  "毎": 390,
  "静": 387,
  "搬": 386,
  "央": 385,
  "境": 383,
  "響": 379,
  "岐": 378,
  "階": 378,
  "聞": 378,
  "三": 375,
  "蔵": 375,
  "攻": 371,
  "粉": 368,
  "復": 367,
  "既": 366,
  "蛍": 365,
  "映": 363,
  "落": 361,
  "宜": 360,
  "群": 360,
  "伴": 359,
  "鉄": 356,
  "降": 355,
  "験": 355,
  "足": 355,
  "蓄": 353,
  "戸": 353,
  "習": 347,
  "呼": 344,
  "醒": 342,
  "兄": 341,
  "緩": 340,
  "燃": 339,
  "太": 339,
  "閉": 337,
  "昇": 335,
  "逃": 334,
  "頭": 331,
  "維": 329,
  "剤": 328,
  "団": 328,
  "埋": 328,
  "壊": 327,
  "環": 326,
  "急": 326,
  "費": 324,
  "継": 323,
  "真": 323,
  "況": 322,
  "頼": 318,
  "堆": 317,
  "枠": 314,
  "官": 313,
  "挙": 309,
  "天": 308,
  "追": 308,
  "窒": 307,
  "顔": 305,
  "敵": 304,
  "垂": 300,
  "仮": 297,
  "脈": 296,
  "傍": 294,
  "歩": 294,
  "親": 292,
  "為": 291,
  "勝": 291,
  "神": 289,
  "寸": 288,
  "溝": 286,
  "即": 286,
  "田": 286,
  "母": 285,
  "還": 283,
  "座": 283,
  "因": 279,
  "推": 276,
  "運": 276,
  "早": 276,
  "騎": 275,
  "致": 274,
  "帰": 274,
  "政": 273,
  "木": 271,
  "四": 270,
  "念": 269,
  "犯": 268,
  "節": 268,
  "途": 268,
  "飛": 267,
  "盤": 261,
  "然": 259,
  "櫛": 258,
  "永": 258,
  "鳴": 258,
  "狭": 257,
  "皇": 251,
  "紙": 251,
  "踏": 250,
  "社": 249,
  "枚": 247,
  "避": 247,
  "伸": 243,
  "修": 243,
  "滑": 240,
  "頻": 238,
  "票": 238,
  "渡": 237,
  "家": 234,
  "陽": 233,
  "償": 233,
  "至": 232,
  "笑": 231,
  "採": 230,
  "歴": 230,
  "銅": 229,
  "暗": 226,
  "律": 224,
  "屈": 224,
  "版": 223,
  "景": 223,
  "坦": 218,
  "証": 218,
  "山": 218,
  "剥": 216,
  "貼": 214,
  "便": 214,
  "似": 214,
  "役": 214,
  "守": 214,
  "食": 214,
  "室": 213,
  "軽": 212,
  "島": 211,
  "矩": 210,
  "抜": 210,
  "帝": 209,
  "丈": 209,
  "拠": 208,
  "爆": 207,
  "勢": 205,
  "織": 205,
  "窓": 204,
  "硬": 204,
  "脳": 203,
  "銃": 200,
  "済": 200,
  "片": 198,
  "村": 198,
  "締": 196,
  "案": 195,
  "弱": 195,
  "統": 194,
  "若": 194,
  "箇": 190,
  "月": 190,
  "屑": 189,
  "履": 188,
  "核": 187,
  "教": 187,
  "械": 185,
  "研": 185,
  "泉": 184,
  "殿": 182,
  "海": 182,
  "独": 181,
  "筒": 180,
  "弦": 179,
  "華": 179,
  "架": 178,
  "揮": 178,
  "跡": 178,
  "兵": 178,
  "搭": 177,
  "秒": 177,
  "務": 177,
  "功": 175,
  "矢": 174,
  "柱": 174,
  "包": 173,
  "商": 173,
  "奴": 172,
  "掛": 172,
  "或": 171,
  "枢": 171,
  "監": 171,
  "隠": 171,
  "駄": 170,
  "害": 169,
  "歯": 168,
  "慮": 168,
  "捜": 167,
  "貴": 166,
  "善": 165,
  "往": 165,
  "奥": 164,
  "倒": 163,
  "遠": 161,
  "且": 160,
  "投": 160,
  "隙": 159,
  "緒": 157,
  "産": 155,
  "救": 155,
  "打": 154,
  "腕": 153,
  "議": 152,
  "染": 151,
  "撓": 150,
  "旨": 150,
  "留": 150,
  "疑": 149,
  "恐": 149,
  "航": 148,
  "傷": 148,
  "町": 148,
  "橋": 147,
  "兼": 146,
  "拍": 146,
  "父": 145,
  "依": 145,
  "狙": 145,
  "摺": 144,
  "湾": 144,
  "鎖": 144,
  "荒": 144,
  "鉛": 143,
  "額": 143,
  "武": 143,
  "督": 142,
  "陥": 142,
  "摩": 141,
  "権": 141,
  "討": 141,
  "援": 139,
  "双": 139,
  "売": 139,
  "危": 139,
  "夢": 138,
  "余": 138,
  "衝": 138,
  "嘘": 137,
  "瞬": 137,
  "担": 136,
  "訳": 136,
  "尚": 135,
  "米": 135,
  "剣": 134,
  "写": 133,
  "敗": 133,
  "居": 133,
  "仲": 133,
  "序": 132,
  "火": 132,
  "石": 131,
  "友": 131,
  "姿": 131,
  "抽": 130,
  "激": 130,
  "探": 129,
  "働": 128,
  "砕": 127,
  "薬": 127,
  "庁": 126,
  "瞳": 126,
  "侵": 123,
  "吐": 123,
  "治": 123,
  "犠": 122,
  "牲": 122,
  "嫌": 122,
  "填": 121,
  "故": 121,
  "首": 121,
  "府": 120,
  "伏": 120,
  "己": 120,
  "堂": 119,
  "塩": 118,
  "漏": 118,
  "縮": 118,
  "遊": 118,
  "困": 118,
  "粘": 117,
  "究": 115,
  "馬": 115,
  "捨": 115,
  "劣": 114,
  "夜": 114,
  "油": 113,
  "潜": 113,
  "滅": 113,
  "痛": 113,
  "北": 112,
  "乃": 111,
  "争": 111,
  "雰": 110,
  "臣": 110,
  "屋": 110,
  "族": 110,
  "欲": 110,
  "乾": 108,
  "索": 108,
  "奪": 107,
  "繋": 106,
  "爪": 106,
  "鑑": 106,
  "禁": 106,
  "悲": 105,
  "罪": 104,
  "握": 104,
  "根": 104,
  "葉": 104,
  "怖": 104,
  "卿": 103,
  "把": 103,
  "愛": 103,
  "礼": 103,
  "忘": 103,
  "衰": 102,
  "策": 102,
  "鹿": 101,
  "暴": 101,
  "亘": 100,
  "逸": 100,
  "肉": 98,
  "邦": 97,
  "遣": 97,
  "雑": 97,
  "卜": 96,
  "穴": 96,
  "螺": 95,
  "越": 95,
  "迷": 95,
  "闘": 95,
  "虹": 94,
  "派": 94,
  "焦": 94,
  "協": 94,
  "累": 93,
  "粗": 92,
  "秘": 92,
  "浮": 92,
  "血": 92,
  "昨": 91,
  "頂": 90,
  "奇": 90,
  "皆": 90,
  "但": 89,
  "湿": 89,
  "耗": 89,
  "灯": 89,
  "占": 89,
  "尾": 89,
  "希": 89,
  "久": 89,
  "滴": 88,
  "弁": 88,
  "零": 88,
  "申": 88,
  "苦": 88,
  "扇": 87,
  "沢": 87,
  "険": 87,
  "司": 87,
  "著": 86,
  "浸": 86,
  "軌": 86,
  "銀": 86,
  "展": 85,
  "舌": 85,
  "燥": 85,
  "陣": 85,
  "万": 85,
  "盗": 85,
  "泣": 85,
  "呈": 84,
  "築": 84,
  "艦": 83,
  "資": 83,
  "美": 83,
  "斗": 82,
  "稼": 82,
  "亡": 82,
  "普": 82,
  "歪": 81,
  "徒": 81,
  "英": 81,
  "黙": 81,
  "懸": 81,
  "幸": 81,
  "刺": 81,
  "昔": 80,
  "陛": 79,
  "紅": 79,
  "洗": 79,
  "鮮": 78,
  "黄": 76,
  "隅": 76,
  "住": 76,
  "嵌": 75,
  "趣": 75,
  "脅": 75,
  "週": 75,
  "球": 74,
  "将": 74,
  "専": 74,
  "症": 74,
  "跳": 74,
  "障": 74,
  "襲": 74,
  "括": 73,
  "雄": 73,
  "陸": 73,
  "塞": 73,
  "惑": 73,
  "眠": 73,
  "頃": 73,
  "棒": 72,
  "班": 72,
  "志": 72,
  "休": 72,
  "邪": 72,
  "磨": 71,
  "騒": 71,
  "扱": 70,
  "潰": 70,
  "悟": 70,
  "斬": 70,
  "級": 69,
  "語": 69,
  "郎": 69,
  "枝": 68,
  "併": 68,
  "氏": 68,
  "絞": 67,
  "船": 67,
  "衆": 67,
  "徐": 67,
  "客": 67,
  "弧": 66,
  "蒸": 66,
  "刑": 66,
  "朝": 66,
  "聖": 66,
  "融": 65,
  "臓": 65,
  "霊": 64,
  "姉": 64,
  "土": 63,
  "裂": 63,
  "盛": 62,
  "迫": 62,
  "弟": 62,
  "賊": 62,
  "偽": 61,
  "興": 61,
  "談": 61,
  "典": 60,
  "園": 60,
  "博": 60,
  "幽": 60,
  "忠": 59,
  "責": 59,
  "労": 59,
  "則": 58,
  "猫": 58,
  "獲": 58,
  "招": 58,
  "痕": 58,
  "迎": 58,
  "脚": 57,
  "瀬": 57,
  "病": 57,
  "絵": 56,
  "租": 56,
  "慧": 56,
  "六": 55,
  "花": 55,
  "企": 55,
  "曽": 55,
  "咲": 55,
  "随": 55,
  "輪": 54,
  "臨": 54,
  "館": 54,
  "擬": 54,
  "東": 54,
  "汚": 54,
  "甘": 54,
  "筺": 53,
  "擦": 53,
  "寿": 53,
  "骨": 53,
  "王": 53,
  "阻": 52,
  "拘": 52,
  "師": 52,
  "丸": 52,
  "謝": 52,
  "網": 51,
  "娘": 51,
  "執": 51,
  "街": 50,
  "諸": 50,
  "遺": 50,
  "怒": 50,
  "厳": 50,
  "勿": 49,
  "紫": 49,
  "蓮": 49,
  "緊": 49,
  "飽": 49,
  "庫": 49,
  "偶": 49,
  "妨": 48,
  "床": 48,
  "医": 48,
  "崩": 48,
  "劇": 48,
  "愚": 48,
  "殴": 48,
  "拾": 48,
  "飲": 48,
  "服": 48,
  "緻": 47,
  "淡": 47,
  "如": 47,
  "港": 47,
  "契": 47,
  "院": 47,
  "孤": 47,
  "届": 47,
  "尺": 46,
  "砲": 46,
  "建": 46,
  "輩": 46,
  "尽": 46,
  "宿": 46,
  "腐": 45,
  "株": 45,
  "城": 45,
  "職": 45,
  "承": 45,
  "南": 45,
  "輸": 44,
  "浄": 44,
  "逮": 44,
  "療": 44,
  "耳": 44,
  "妹": 44,
  "殊": 44,
  "妙": 44,
  "窪": 43,
  "汎": 43,
  "殻": 43,
  "譜": 43,
  "革": 43,
  "千": 43,
  "買": 43,
  "借": 43,
  "寝": 43,
  "払": 43,
  "桁": 43,
  "稜": 42,
  "緯": 42,
  "閣": 42,
  "覧": 42,
  "古": 42,
  "筋": 42,
  "昭": 41,
  "殆": 41,
  "疎": 41,
  "候": 41,
  "暮": 41,
  "喜": 41,
  "泳": 40,
  "裁": 40,
  "房": 40,
  "涙": 40,
  "揺": 40,
  "預": 40,
  "宣": 39,
  "歳": 39,
  "委": 39,
  "冗": 39,
  "勾": 38,
  "菱": 38,
  "乏": 38,
  "審": 38,
  "剰": 38,
  "戒": 38,
  "炉": 37,
  "塑": 37,
  "販": 37,
  "旦": 37,
  "姫": 37,
  "婚": 37,
  "聴": 37,
  "玉": 37,
  "匹": 37,
  "洞": 36,
  "逐": 36,
  "舞": 36,
  "草": 36,
  "県": 36,
  "浅": 36,
  "頑": 36,
  "旅": 36,
  "麻": 35,
  "驚": 35,
  "悔": 35,
  "腹": 35,
  "祭": 35,
  "誉": 34,
  "貯": 34,
  "虐": 34,
  "錯": 34,
  "盾": 34,
  "詰": 34,
  "遭": 34,
  "狂": 34,
  "揃": 33,
  "店": 33,
  "授": 33,
  "帽": 33,
  "訓": 33,
  "駒": 33,
  "威": 33,
  "幹": 32,
  "柄": 32,
  "拐": 32,
  "悩": 32,
  "釈": 32,
  "闇": 32,
  "怪": 32,
  "懐": 32,
  "吊": 31,
  "爵": 31,
  "才": 31,
  "貸": 31,
  "羽": 31,
  "旧": 31,
  "育": 31,
  "抱": 31,
  "勘": 31,
  "栖": 30,
  "嚮": 30,
  "百": 30,
  "毒": 30,
  "誇": 30,
  "老": 30,
  "編": 30,
  "循": 29,
  "春": 29,
  "卑": 29,
  "罰": 29,
  "勇": 29,
  "富": 29,
  "岸": 29,
  "遂": 29,
  "謀": 29,
  "清": 29,
  "五": 29,
  "狩": 29,
  "濡": 28,
  "箱": 28,
  "虎": 28,
  "逢": 28,
  "廃": 28,
  "茶": 28,
  "川": 28,
  "看": 28,
  "憎": 28,
  "皮": 28,
  "棄": 28,
  "幻": 28,
  "恋": 27,
  "礎": 27,
  "漬": 27,
  "撤": 27,
  "夏": 27,
  "裕": 27,
  "胞": 27,
  "穏": 27,
  "暇": 27,
  "枕": 26,
  "倣": 26,
  "是": 26,
  "党": 26,
  "翼": 26,
  "耶": 26,
  "門": 26,
  "午": 26,
  "堀": 26,
  "芸": 26,
  "剛": 25,
  "硫": 25,
  "旋": 25,
  "仇": 25,
  "宦": 25,
  "鋭": 25,
  "曜": 25,
  "慰": 25,
  "酔": 25,
  "快": 25,
  "臭": 25,
  "渣": 24,
  "促": 24,
  "茅": 24,
  "葺": 24,
  "辻": 24,
  "紹": 24,
  "績": 24,
  "轄": 24,
  "鈴": 24,
  "倉": 24,
  "史": 24,
  "秀": 24,
  "唯": 24,
  "洩": 23,
  "須": 23,
  "京": 23,
  "措": 23,
  "庭": 23,
  "彩": 23,
  "掃": 23,
  "徹": 23,
  "慢": 23,
  "叫": 23,
  "魚": 23,
  "撹": 22,
  "妥": 22,
  "洋": 22,
  "斉": 22,
  "席": 22,
  "扉": 22,
  "創": 22,
  "慎": 22,
  "挑": 22,
  "惜": 22,
  "刀": 22,
  "諦": 22,
  "眼": 22,
  "拌": 21,
  "浜": 21,
  "僅": 21,
  "巡": 21,
  "伯": 21,
  "訴": 21,
  "掘": 21,
  "健": 21,
  "癒": 21,
  "敢": 21,
  "掴": 21,
  "恥": 21,
  "嬢": 21,
  "鳥": 21,
  "讐": 21,
  "飯": 21,
  "児": 21,
  "八": 21,
  "蹴": 21,
  "飾": 20,
  "噂": 20,
  "弐": 20,
  "叩": 20,
  "宇": 20,
  "宙": 20,
  "植": 20,
  "科": 20,
  "蔽": 20,
  "州": 20,
  "犬": 20,
  "堪": 20,
  "叶": 20,
  "章": 20,
  "誓": 20,
  "哀": 20,
  "慣": 20,
  "敷": 20,
  "飼": 20,
  "疲": 20,
  "偵": 20,
  "遇": 20,
  "珍": 20,
  "偉": 20,
  "郭": 19,
  "瞰": 19,
  "鋼": 19,
  "誠": 19,
  "辞": 19,
  "晴": 19,
  "賛": 19,
  "奈": 19,
  "獄": 19,
  "栄": 19,
  "寂": 19,
  "婦": 19,
  "柔": 19,
  "西": 19,
  "雷": 19,
  "獅": 19,
  "虞": 18,
  "撥": 18,
  "香": 18,
  "軟": 18,
  "播": 18,
  "税": 18,
  "翻": 18,
  "七": 18,
  "潔": 18,
  "虜": 18,
  "騙": 18,
  "億": 18,
  "陰": 18,
  "沈": 18,
  "巨": 18,
  "幼": 18,
  "糊": 17,
  "芳": 17,
  "俯": 17,
  "掲": 17,
  "雲": 17,
  "迅": 17,
  "紀": 17,
  "唱": 17,
  "駅": 17,
  "怯": 17,
  "亀": 17,
  "診": 17,
  "昼": 17,
  "財": 17,
  "賞": 17,
  "凡": 17,
  "紋": 17,
  "慌": 17,
  "譲": 17,
  "魂": 17,
  "箔": 16,
  "雌": 16,
  "塵": 16,
  "廷": 16,
  "卒": 16,
  "獨": 16,
  "准": 16,
  "福": 16,
  "槌": 16,
  "恨": 16,
  "甲": 16,
  "孫": 16,
  "蛮": 16,
  "鍋": 16,
  "楼": 16,
  "謎": 16,
  "褒": 16,
  "夕": 16,
  "醜": 16,
  "淵": 16,
  "鍔": 15,
  "擂": 15,
  "瞭": 15,
  "鋸": 15,
  "輔": 15,
  "冠": 15,
  "塔": 15,
  "鶴": 15,
  "蝶": 15,
  "蜃": 15,
  "灰": 15,
  "袋": 15,
  "賭": 15,
  "邸": 15,
  "誕": 15,
  "益": 15,
  "噛": 15,
  "宅": 15,
  "雨": 15,
  "尻": 15,
  "肢": 15,
  "敬": 15,
  "養": 15,
  "杯": 15,
  "紛": 15,
  "雪": 15,
  "震": 15,
  "鈍": 15,
  "訪": 15,
  "幕": 15,
  "恩": 15,
  "喰": 15,
  "酢": 14,
  "萎": 14,
  "煩": 14,
  "繁": 14,
  "恒": 14,
  "旗": 14,
  "澤": 14,
  "囚": 14,
  "遵": 14,
  "唆": 14,
  "丁": 14,
  "詮": 14,
  "贈": 14,
  "吠": 14,
  "幾": 14,
  "免": 14,
  "歌": 14,
  "墜": 14,
  "拉": 14,
  "沖": 14,
  "肝": 14,
  "辿": 14,
  "宵": 14,
  "羊": 14,
  "烈": 14,
  "坊": 14,
  "鼻": 14,
  "楕": 13,
  "庇": 13,
  "宛": 13,
  "釣": 13,
  "没": 13,
  "簿": 13,
  "酒": 13,
  "矛": 13,
  "蜂": 13,
  "玄": 13,
  "尉": 13,
  "罠": 13,
  "彷": 13,
  "徨": 13,
  "苛": 13,
  "康": 13,
  "祝": 13,
  "澄": 13,
  "那": 13,
  "拒": 13,
  "拝": 13,
  "九": 13,
  "咽": 13,
  "雫": 13,
  "腰": 13,
  "滞": 13,
  "尊": 13,
  "餌": 13,
  "募": 13,
  "虚": 13,
  "尋": 13,
  "厄": 13,
  "忙": 13,
  "妄": 13,
  "粋": 13,
  "辛": 13,
  "歓": 13,
  "泊": 13,
  "句": 13,
  "錐": 12,
  "跨": 12,
  "賦": 12,
  "捗": 12,
  "唄": 12,
  "顧": 12,
  "胆": 12,
  "云": 12,
  "斑": 12,
  "批": 12,
  "嬉": 12,
  "輻": 12,
  "茜": 12,
  "錦": 12,
  "桐": 12,
  "伺": 12,
  "災": 12,
  "堅": 12,
  "岡": 12,
  "躍": 12,
  "縛": 12,
  "泥": 12,
  "濁": 12,
  "墓": 12,
  "伐": 12,
  "謂": 11,
  "笫": 11,
  "槽": 11,
  "做": 11,
  "酌": 11,
  "籍": 11,
  "憲": 11,
  "湧": 11,
  "駐": 11,
  "札": 11,
  "舎": 11,
  "勉": 11,
  "弊": 11,
  "寒": 11,
  "晩": 11,
  "捩": 10,
  "埃": 10,
  "漸": 10,
  "欄": 10,
  "迄": 10,
  "斥": 10,
  "熟": 10,
  "宗": 10,
  "抹": 10,
  "辱": 10,
  "河": 10,
  "朽": 10,
  "兜": 10,
  "毛": 10,
  "競": 10,
  "貧": 10,
  "喪": 10,
  "桜": 10,
  "渦": 10,
  "雇": 10,
  "酷": 10,
  "儀": 10,
  "嗅": 10,
  "惨": 10,
  "託": 10,
  "逝": 10,
  "尖": 9,
  "錫": 9,
  "峻": 9,
  "篩": 9,
  "錠": 9,
  "丹": 9,
  "稿": 9,
  "帳": 9,
  "閲": 9,
  "唇": 9,
  "就": 9,
  "郷": 9,
  "僚": 9,
  "欺": 9,
  "隷": 9,
  "朱": 9,
  "誌": 9,
  "縄": 9,
  "璧": 9,
  "宮": 9,
  "営": 9,
  "努": 9,
  "覇": 9,
  "寮": 9,
  "脇": 9,
  "患": 9,
  "煙": 9,
  "暖": 9,
  "踊": 9,
  "控": 9,
  "麗": 9,
  "酬": 9,
  "浴": 9,
  "鐘": 9,
  "嵩": 8,
  "窄": 8,
  "綸": 8,
  "賀": 8,
  "赴": 8,
  "催": 8,
  "鬼": 8,
  "猿": 8,
  "嫁": 8,
  "俗": 8,
  "殉": 8,
  "胸": 8,
  "翔": 8,
  "癖": 8,
  "圏": 8,
  "吉": 8,
  "凶": 8,
  "曖": 8,
  "昧": 8,
  "仰": 8,
  "羅": 8,
  "妻": 8,
  "芽": 8,
  "餓": 8,
  "赦": 8,
  "祈": 8,
  "賢": 8,
  "勐": 7,
  "巳": 7,
  "錘": 7,
  "燐": 7,
  "芯": 7,
  "蛇": 7,
  "踪": 7,
  "勧": 7,
  "廊": 7,
  "迭": 7,
  "挨": 7,
  "拶": 7,
  "魅": 7,
  "晒": 7,
  "揚": 7,
  "砂": 7,
  "艇": 7,
  "籠": 7,
  "喧": 7,
  "姻": 7,
  "亭": 7,
  "浪": 7,
  "農": 7,
  "怠": 7,
  "凝": 7,
  "署": 7,
  "倫": 7,
  "畑": 7,
  "暁": 7,
  "机": 7,
  "聡": 7,
  "塊": 7,
  "森": 7,
  "殲": 7,
  "氷": 7,
  "兆": 7,
  "炎": 7,
  "巧": 7,
  "虫": 7,
  "壮": 7,
  "肩": 7,
  "梁": 6,
  "敁": 6,
  "亍": 6,
  "乳": 6,
  "腔": 6,
  "鍮": 6,
  "冪": 6,
  "滲": 6,
  "銭": 6,
  "奉": 6,
  "遥": 6,
  "糸": 6,
  "溜": 6,
  "諾": 6,
  "卓": 6,
  "匿": 6,
  "舗": 6,
  "諜": 6,
  "掌": 6,
  "憂": 6,
  "馴": 6,
  "杉": 6,
  "朗": 6,
  "庶": 6,
  "盟": 6,
  "仙": 6,
  "陵": 6,
  "嘩": 6,
  "宰": 6,
  "溢": 6,
  "褪": 6,
  "繊": 6,
  "綻": 6,
  "摘": 6,
  "潮": 6,
  "林": 6,
  "憩": 6,
  "岩": 6,
  "也": 6,
  "鉢": 6,
  "眺": 6,
  "呪": 6,
  "惚": 6,
  "陳": 6,
  "豪": 6,
  "迂": 6,
  "葬": 6,
  "恵": 6,
  "溺": 6,
  "講": 6,
  "懲": 6,
  "粛": 6,
  "飢": 6,
  "慈": 6,
  "馆": 5,
  "奨": 5,
  "冊": 5,
  "曝": 5,
  "遍": 5,
  "翌": 5,
  "丘": 5,
  "曹": 5,
  "桃": 5,
  "髪": 5,
  "搾": 5,
  "玖": 5,
  "季": 5,
  "豆": 5,
  "凄": 5,
  "賄": 5,
  "享": 5,
  "召": 5,
  "愉": 5,
  "齢": 5,
  "膚": 5,
  "牽": 5,
  "戯": 5,
  "暦": 5,
  "爺": 5,
  "湖": 5,
  "宴": 5,
  "蓬": 5,
  "莱": 5,
  "需": 5,
  "哨": 5,
  "摂": 5,
  "猶": 5,
  "童": 5,
  "肯": 5,
  "屯": 5,
  "椅": 5,
  "瓦": 5,
  "琴": 5,
  "隻": 5,
  "拭": 5,
  "践": 5,
  "乞": 5,
  "綱": 5,
  "涯": 5,
  "獣": 5,
  "窀": 4,
  "躯": 4,
  "增": 4,
  "於": 4,
  "廉": 4,
  "釦": 4,
  "韓": 4,
  "咥": 4,
  "冶": 4,
  "培": 4,
  "皺": 4,
  "潤": 4,
  "秩": 4,
  "禅": 4,
  "凍": 4,
  "傑": 4,
  "薩": 4,
  "玲": 4,
  "芝": 4,
  "汗": 4,
  "栗": 4,
  "箸": 4,
  "粧": 4,
  "豊": 4,
  "敏": 4,
  "伍": 4,
  "祖": 4,
  "僧": 4,
  "噴": 4,
  "蕩": 4,
  "紡": 4,
  "憧": 4,
  "拗": 4,
  "漁": 4,
  "据": 4,
  "贖": 4,
  "矜": 4,
  "弄": 4,
  "堕": 4,
  "悼": 4,
  "呑": 4,
  "妃": 4,
  "侮": 4,
  "閥": 4,
  "鎮": 4,
  "閃": 4,
  "號": 4,
  "鳩": 4,
  "傭": 4,
  "曇": 4,
  "暑": 4,
  "貨": 4,
  "貞": 4,
  "睡": 4,
  "竹": 4,
  "釘": 4,
  "貢": 4,
  "窮": 4,
  "痴": 4,
  "姓": 4,
  "棟": 4,
  "礫": 4,
  "埼": 4,
  "戟": 4,
  "挺": 4,
  "靴": 4,
  "隆": 4,
  "匂": 4,
  "脆": 4,
  "槍": 4,
  "鉱": 4,
  "骸": 4,
  "畜": 4,
  "裸": 4,
  "臆": 4,
  "繕": 4,
  "漣": 4,
  "喉": 4,
  "旭": 3,
  "硝": 3,
  "頁": 3,
  "坩": 3,
  "錆": 3,
  "薪": 3,
  "尿": 3,
  "叉": 3,
  "〇": 3,
  "乙": 3,
  "郵": 3,
  "筆": 3,
  "肥": 3,
  "徳": 3,
  "欧": 3,
  "舷": 3,
  "薦": 3,
  "仏": 3,
  "娯": 3,
  "訟": 3,
  "捏": 3,
  "喋": 3,
  "貿": 3,
  "肺": 3,
  "姐": 3,
  "啓": 3,
  "沼": 3,
  "刊": 3,
  "儲": 3,
  "囁": 3,
  "榊": 3,
  "擁": 3,
  "沙": 3,
  "汰": 3,
  "伊": 3,
  "殖": 3,
  "冬": 3,
  "拷": 3,
  "捧": 3,
  "覗": 3,
  "戚": 3,
  "拳": 3,
  "峙": 3,
  "寧": 3,
  "瞞": 3,
  "妬": 3,
  "哲": 3,
  "糧": 3,
  "蔑": 3,
  "嘆": 3,
  "舵": 3,
  "奸": 3,
  "凱": 3,
  "謹": 3,
  "豚": 3,
  "碑": 3,
  "刹": 3,
  "綺": 3,
  "傲": 3,
  "泰": 3,
  "謁": 3,
  "詫": 3,
  "勲": 3,
  "汝": 3,
  "恭": 3,
  "敦": 3,
  "篠": 3,
  "懺": 3,
  "竜": 3,
  "壱": 3,
  "囮": 3,
  "脊": 3,
  "漫": 3,
  "菜": 3,
  "喩": 3,
  "猛": 3,
  "甚": 3,
  "綿": 3,
  "昏": 3,
  "坑": 3,
  "斐": 3,
  "猟": 3,
  "銘": 3,
  "鍛": 3,
  "巣": 3,
  "稚": 3,
  "慕": 3,
  "奢": 3,
  "渋": 3,
  "嵐": 3,
  "笛": 3,
  "忌": 3,
  "稽": 3,
  "丨": 2,
  "踣": 2,
  "裙": 2,
  "勦": 2,
  "站": 2,
  "允": 2,
  "箅": 2,
  "叨": 2,
  "乖": 2,
  "濾": 2,
  "艤": 2,
  "纏": 2,
  "毀": 2,
  "鋳": 2,
  "堝": 2,
  "絨": 2,
  "莫": 2,
  "阿": 2,
  "蓑": 2,
  "牡": 2,
  "蠣": 2,
  "愁": 2,
  "詞": 2,
  "鞍": 2,
  "椎": 2,
  "憑": 2,
  "暫": 2,
  "糾": 2,
  "奮": 2,
  "里": 2,
  "購": 2,
  "仄": 2,
  "膝": 2,
  "撼": 2,
  "侠": 2,
  "婆": 2,
  "賃": 2,
  "薙": 2,
  "轟": 2,
  "秋": 2,
  "轢": 2,
  "濯": 2,
  "只": 2,
  "嫉": 2,
  "麺": 2,
  "貰": 2,
  "蝕": 2,
  "姑": 2,
  "廻": 2,
  "烏": 2,
  "苗": 2,
  "罵": 2,
  "牛": 2,
  "皿": 2,
  "涜": 2,
  "艘": 2,
  "卵": 2,
  "賂": 2,
  "捻": 2,
  "征": 2,
  "衣": 2,
  "灘": 2,
  "庸": 2,
  "怨": 2,
  "賜": 2,
  "冒": 2,
  "屍": 2,
  "拓": 2,
  "塾": 2,
  "寺": 2,
  "秤": 2,
  "詐": 2,
  "叱": 2,
  "擲": 2,
  "嫡": 2,
  "惰": 2,
  "后": 2,
  "訂": 2,
  "儚": 2,
  "勅": 2,
  "峰": 2,
  "劫": 2,
  "倖": 2,
  "棺": 2,
  "鹵": 2,
  "賓": 2,
  "洛": 2,
  "竿": 2,
  "蟻": 2,
  "憐": 2,
  "松": 2,
  "岳": 2,
  "悠": 2,
  "髄": 2,
  "窃": 2,
  "湯": 2,
  "榴": 2,
  "糖": 2,
  "耕": 2,
  "江": 2,
  "谷": 2,
  "梨": 2,
  "栓": 2,
  "腎": 2,
  "剖": 2,
  "某": 2,
  "慶": 2,
  "祐": 2,
  "胴": 2,
  "痍": 2,
  "寵": 2,
  "渇": 2,
  "拙": 2,
  "狡": 2,
  "猾": 2,
  "牙": 2,
  "謳": 2,
  "袖": 2,
  "菌": 2,
  "躊": 2,
  "躇": 2,
  "盆": 2,
  "弔": 2,
  "娼": 2,
  "隼": 2,
  "肪": 1,
  "漂": 1,
  "椀": 1,
  "紐": 1,
  "圃": 1,
  "侦": 1,
  "縱": 1,
  "蚰": 1,
  "墦": 1,
  "蒂": 1,
  "实": 1,
  "茂": 1,
  "誼": 1,
  "值": 1,
  "逹": 1,
  "翅": 1,
  "串": 1,
  "圯": 1,
  "闵": 1,
  "朿": 1,
  "铯": 1,
  "设": 1,
  "碴": 1,
  "馎": 1,
  "舛": 1,
  "迪": 1,
  "囡": 1,
  "冋": 1,
  "压": 1,
  "筇": 1,
  "灾": 1,
  "乘": 1,
  "迮": 1,
  "粜": 1,
  "银": 1,
  "爾": 1,
  "遛": 1,
  "蛟": 1,
  "录": 1,
  "眩": 1,
  "彫": 1,
  "碁": 1,
  "珠": 1,
  "濱": 1,
  "孝": 1,
  "劈": 1,
  "絳": 1,
  "藪": 1,
  "斯": 1,
  "鍍": 1,
  "匠": 1,
  "厨": 1,
  "靱": 1,
  "錬": 1,
  "攪": 1,
  "氮": 1,
  "耝": 1,
  "枯": 1,
  "祥": 1,
  "凪": 1,
  "魄": 1,
  "煉": 1,
  "津": 1,
  "智": 1,
  "騰": 1,
  "煮": 1,
  "詈": 1,
  "挫": 1,
  "焉": 1,
  "茸": 1,
  "侶": 1,
  "貌": 1,
  "莢": 1,
  "嗜": 1,
  "忍": 1,
  "毯": 1,
  "墟": 1,
  "訣": 1,
  "賑": 1,
  "悦": 1,
  "穫": 1,
  "禍": 1,
  "鶏": 1,
  "揉": 1,
  "峠": 1,
  "憤": 1,
  "疾": 1,
  "泌": 1,
  "牧": 1,
  "鯨": 1,
  "蒙": 1,
  "嚇": 1,
  "礁": 1,
  "函": 1,
  "漕": 1,
  "畏": 1,
  "縷": 1,
  "柳": 1,
  "塚": 1,
  "虱": 1,
  "玩": 1,
  "喝": 1,
  "彦": 1,
  "忽": 1,
  "戴": 1,
  "郊": 1,
  "菓": 1,
  "痩": 1,
  "董": 1,
  "徘": 1,
  "徊": 1,
  "眉": 1,
  "頬": 1,
  "酵": 1,
  "甥": 1,
  "鴉": 1,
  "套": 1,
  "惧": 1,
  "芋": 1,
  "腫": 1,
  "瘍": 1,
  "薫": 1,
  "顛": 1,
  "醸": 1,
  "喚": 1,
  "些": 1,
  "腸": 1,
  "慨": 1,
  "奔": 1,
  "垢": 1,
  "噌": 1,
  "恣": 1,
  "堤": 1,
  "鮫": 1,
  "顎": 1,
  "撫": 1,
  "熊": 1,
  "悶": 1,
  "稲": 1,
  "洒": 1,
  "筈": 1,
  "祷": 1,
  "侯": 1,
  "嗟": 1,
  "呆": 1,
  "埒": 1,
  "頓": 1,
  "這": 1,
  "盲": 1,
  "祉": 1,
  "撲": 1,
  "呂": 1,
  "瓶": 1,
  "荘": 1,
  "鎧": 1,
  "麓": 1,
  "宝": 1,
  "馳": 1,
  "綴": 1,
  "掻": 1,
  "垣": 1,
  "淀": 1,
  "克": 1,
  "謙": 1,
  "鷹": 1,
  "蔓": 1,
  "腑": 1,
  "崚": 1,
  "絆": 1,
  "叙": 1,
  "糞": 1,
  "侍": 1,
  "勃": 1,
  "楔": 1,
  "癪": 1,
  "燕": 1,
  "袈": 1,
  "裟": 1,
  "矯": 1,
  "虽": 1,
  "截": 1,
  "吏": 1,
  "棘": 1,
  "雀": 1,
  "肖": 1,
  "誅": 1,
  "葡": 1,
  "萄": 1,
  "邁": 1,
  "亥": 1,
  "幡": 1,
  "兎": 1,
  "姦": 1,
  "淫": 1,
  "麦": 1,
  "贋": 1,
  "寛": 1,
  "蘇": 1,
  "鳳": 1,
  "凰": 1,
  "諍": 1,
  "杞": 1,
  "趙": 1,
  "皓": 1,
  "渓": 1,
  "沛": 1,
  "愕": 1,
  "猪": 1,
  "灌": 1,
  "漑": 1,
  "膠": 1,
  "詩": 1,
  "滝": 1,
  "痺": 1,
  "羨": 1,
  "坤": 1,
  "汲": 1,
  "縫": 1,
  "趨": 1,
  "蹂": 1,
  "躙": 1,
  "畢": 1,
  "竟": 1,
  "麒": 1,
  "麟": 1,
  "朴": 1,
  "仁": 1,
  "牢": 1,
  "而": 1,
  "簒": 1,
  "弓": 1,
  "凌": 1,
  "駕": 1,
  "漢": 1,
  "檻": 1,
  "拿": 1,
  "稀": 1,
  "昆": 1,
  "鉗": 1,
  "幇": 1,
  "缶": 1,
  "披": 1,
  "盪": 1,
  "唾": 1,
  "崇": 1,
  "刈": 1,
  "李": 1,
  "毅": 1,
  "阪": 1,
  "柏": 1,
  "霧": 1,
  "壕": 1,
  "爽": 1,
  "戮": 1,
  "疫": 1,
  "恍": 1,
  "屁": 1,
  "餞": 1,
  "渾": 1,
  "邂": 1,
  "逅": 1,
  "躱": 1,
  "冥": 1,
  "俵": 1,
  "抉": 1,
  "碌": 1,
  "縋": 1,
  "嬲": 1,
  "咆": 1,
  "哮": 1,
  "俄": 1,
  "轍": 1,
  "艶": 1
}